{"hospital_001":{"hospitalId":"hospital_001","name":"Shaukat Khanum Hospital","address":"Johar Town, Lahore","description":"Cancer research hospital and diagnostic centre.","imageUrl":"https://upload.wikimedia.org/wikipedia/commons/e/e0/Shaukat_Khanum_Memorial_Cancer_Hospital_%26_Research_Centre_Lahore.jpg","rating":4.8,"latitude":31.4554,"longitude":74.2690,"distanceMiles":2.5,"specialties":["Oncology","Radiology","Diagnostic"],"waitTime":15,"rooms":{"room_001":{"roomId":"room_001","roomNumber":"101","type":"General","pricePerDay":2000.0,"isAvailable":true},"room_002":{"roomId":"room_002","roomNumber":"102","type":"Private","pricePerDay":8000.0,"isAvailable":true},"room_003":{"roomId":"room_003","roomNumber":"ICU-1","type":"ICU","pricePerDay":15000.0,"isAvailable":true}}},"hospital_002":{"hospitalId":"hospital_002","name":"Doctors Hospital","address":"Johar Town, Lahore","description":"State-of-the-art modern medical facilities.","imageUrl":"https://images.unsplash.com/photo-1519494026892-80bbd2d6fd0d?w=800&q=80","rating":4.6,"latitude":31.4633,"longitude":74.2687,"distanceMiles":3.0,"specialties":["Cardiology","Neurology","Orthopedics"],"waitTime":20,"rooms":{"room_001":{"roomId":"room_001","roomNumber":"201","type":"General","pricePerDay":2500.0,"isAvailable":true},"room_002":{"roomId":"room_002","roomNumber":"202","type":"Private","pricePerDay":9000.0,"isAvailable":true},"room_003":{"roomId":"room_003","roomNumber":"ICU-2","type":"ICU","pricePerDay":18000.0,"isAvailable":true}}},"hospital_003":{"hospitalId":"hospital_003","name":"Combined Military Hospital (CMH)","address":"Cantonment, Lahore","description":"Premium military and civilian medical center.","imageUrl":"https://images.unsplash.com/photo-1586773860418-d37222d8fce3?w=800&q=80","rating":4.7,"latitude":31.5230,"longitude":74.3756,"distanceMiles":5.2,"specialties":["Surgery","Trauma","General Medicine"],"waitTime":30,"rooms":{"room_001":{"roomId":"room_001","roomNumber":"A1","type":"General","pricePerDay":1500.0,"isAvailable":true},"room_002":{"roomId":"room_002","roomNumber":"P1","type":"Private","pricePerDay":7000.0,"isAvailable":true}}},"hospital_004":{"hospitalId":"hospital_004","name":"Hameed Latif Hospital","address":"Gaddafi Stadium Road, Lahore","description":"Leading healthcare provider known for excellent patient care.","imageUrl":"https://images.unsplash.com/photo-1516549655169-df83a0774514?w=800&q=80","rating":4.5,"latitude":31.5126,"longitude":74.3314,"distanceMiles":4.1,"specialties":["Gynaecology","Pediatrics","Cardiology"],"waitTime":25,"rooms":{"room_001":{"roomId":"room_001","roomNumber":"301","type":"General","pricePerDay":2200.0,"isAvailable":true},"room_002":{"roomId":"room_002","roomNumber":"302","type":"Private","pricePerDay":8500.0,"isAvailable":true}}},"hospital_005":{"hospitalId":"hospital_005","name":"National Hospital & Medical Centre","address":"DHA Phase 1, Lahore","description":"Comprehensive medical services in the heart of DHA.","imageUrl":"https://images.unsplash.com/photo-1504439468489-c8920d786a2b?w=800&q=80","rating":4.4,"latitude":31.4725,"longitude":74.3888,"distanceMiles":6.0,"specialties":["Orthopedics","Dentistry","Dermatology"],"waitTime":10,"rooms":{"room_001":{"roomId":"room_001","roomNumber":"401","type":"General","pricePerDay":3000.0,"isAvailable":true},"room_002":{"roomId":"room_002","roomNumber":"402","type":"Private","pricePerDay":10000.0,"isAvailable":true}}},"hospital_006":{"hospitalId":"hospital_006","name":"Jinnah Hospital","address":"Quaid-e-Azam Campus, Lahore","description":"Large public sector hospital providing tertiary care.","imageUrl":"https://images.unsplash.com/photo-1538108149393-fbbd81895907?w=800&q=80","rating":4.1,"latitude":31.4883,"longitude":74.2952,"distanceMiles":3.5,"specialties":["Emergency","Surgery","Internal Medicine"],"waitTime":45,"rooms":{"room_001":{"roomId":"room_001","roomNumber":"W1","type":"General","pricePerDay":500.0,"isAvailable":true},"room_002":{"roomId":"room_002","roomNumber":"P5","type":"Private","pricePerDay":4000.0,"isAvailable":true}}},"hospital_007":{"hospitalId":"hospital_007","name":"Farooq Hospital","address":"Allama Iqbal Town, Lahore","description":"Trusted healthcare facility with modern amenities.","imageUrl":"https://images.unsplash.com/photo-1579684385127-1ef15d508118?w=800&q=80","rating":4.3,"latitude":31.5035,"longitude":74.2831,"distanceMiles":4.8,"specialties":["Urology","Nephrology","General Surgery"],"waitTime":20,"rooms":{"room_001":{"roomId":"room_001","roomNumber":"501","type":"General","pricePerDay":1800.0,"isAvailable":true},"room_002":{"roomId":"room_002","roomNumber":"502","type":"Private","pricePerDay":6500.0,"isAvailable":true}}},"hospital_008":{"hospitalId":"hospital_008","name":"Services Hospital","address":"Jail Road, Lahore","description":"Prominent teaching hospital affiliated with SIMS.","imageUrl":"https://images.unsplash.com/photo-1512678080530-7760d81faba6?w=800&q=80","rating":4.0,"latitude":31.5369,"longitude":74.3400,"distanceMiles":5.5,"specialties":["Neurology","Psychiatry","Endocrinology"],"waitTime":60,"rooms":{"room_001":{"roomId":"room_001","roomNumber":"W3","type":"General","pricePerDay":600.0,"isAvailable":true},"room_002":{"roomId":"room_002","roomNumber":"P10","type":"Private","pricePerDay":5000.0,"isAvailable":true}}},"hospital_009":{"hospitalId":"hospital_009","name":"Surgimed Hospital","address":"Zafar Ali Road, Lahore","description":"Multi-specialty hospital with advanced surgical units.","imageUrl":"https://images.unsplash.com/photo-1512820790803-83ca734da794?w=800&q=80","rating":4.2,"latitude":31.5385,"longitude":74.3490,"distanceMiles":6.2,"specialties":["Plastic Surgery","ENT","Orthopedics"],"waitTime":15,"rooms":{"room_001":{"roomId":"room_001","roomNumber":"601","type":"General","pricePerDay":2800.0,"isAvailable":true},"room_002":{"roomId":"room_002","roomNumber":"602","type":"Private","pricePerDay":9500.0,"isAvailable":true}}},"hospital_010":{"hospitalId":"hospital_010","name":"Fatima Memorial Hospital","address":"Shadman, Lahore","description":"Not-for-profit hospital dedicated to quality care.","imageUrl":"https://images.unsplash.com/photo-1632833239869-a37e3a5806d2?w=800&q=80","rating":4.5,"latitude":31.5317,"longitude":74.3211,"distanceMiles":4.5,"specialties":["Maternal Health","Pediatrics","Dentistry"],"waitTime":25,"rooms":{"room_001":{"roomId":"room_001","roomNumber":"701","type":"General","pricePerDay":1200.0,"isAvailable":true},"room_002":{"roomId":"room_002","roomNumber":"702","type":"Private","pricePerDay":5500.0,"isAvailable":true}}}}
